aiotainer/__init__.py
aiotainer/auth.py
aiotainer/client.py
aiotainer/const.py
aiotainer/exceptions.py
aiotainer/model.py
aiotainer/portainer_settings.py
aiotainer/py.typed
aiotainer/utils.py
aiotainer-0.0.1b6.dist-info/LICENSE
aiotainer-0.0.1b6.dist-info/METADATA
aiotainer-0.0.1b6.dist-info/WHEEL
aiotainer-0.0.1b6.dist-info/RECORD
