Metadata-Version: 2.3
Name: aiotainer
Version: 0.0.1b6
Summary: MPython module to talk to a Portainer.
License: MIT
Keywords: Portainer,Docker,api,async,client
Author: Thomas Peter Protzner
Author-email: thomas.protzner@gmail.com
Requires-Python: >=3.11,<4.0
Classifier: Development Status :: 5 - Production/Stable
Classifier: Framework :: AsyncIO
Classifier: Intended Audience :: Developers
Classifier: License :: OSI Approved :: MIT License
Classifier: Natural Language :: English
Classifier: Programming Language :: Python :: 3
Classifier: Programming Language :: Python :: 3.11
Classifier: Programming Language :: Python :: 3.12
Classifier: Programming Language :: Python :: 3.13
Classifier: Topic :: Software Development :: Libraries :: Python Modules
Requires-Dist: aiohttp (>=3.9.3,<4.0.0)
Requires-Dist: mashumaro (>=3.12,<4.0)
Project-URL: Documentation, https://github.com/Thomas55555/aiotainer
Project-URL: Homepage, https://github.com/Thomas55555/aiotainer
Project-URL: Issues, https://github.com/Thomas55555/aiotainer/issues
Project-URL: Repository, https://github.com/Thomas55555/aiotainer
